bolor/__init__.py
bolor/__main__.py
bolor/__main__py.py
bolor/cli.py
bolor/agent/__init__.py
bolor/agent/dataset_loader.py
bolor/agent/fixer.py
bolor/agent/generator.py
bolor/agent/llm_wrapper.py
bolor/agent/models.py
bolor/agent/planner.py
bolor/agent/scanner.py
bolor/bolor/__init__.py
bolor/bolor/__main__.py
bolor/evolution/__init__.py
bolor/evolution/candidate.py
bolor/utils/__init__.py
bolor/utils/config.py
bolor-0.2.7.data/scripts/bolor-cli
bolor-0.2.7.data/scripts/bolor-wrap
bolor_core/__init__.py
bolor_core/code_checker.py
bolor_core/gguf_downloader.py
bolor_core/git_utils.py
bolor_core/llm_runner.py
bolor_core/symbol_map.py
bolor_core/validator.py
keep_files/CHANGELOG.md
keep_files/LICENSE
keep_files/README.md
keep_files/__init__.py
keep_files/__main__.py
keep_files/buggy_code.py
keep_files/build_and_upload.sh
keep_files/clean-setup.sh
keep_files/deploy-bolor.py
keep_files/deploy-to-pypi.sh
keep_files/nlp_interface_example.py
keep_files/nlp_interface_example_patched.py
keep_files/patch_requests.py
keep_files/requirements.txt
keep_files/setup.py
keep_files/test-bolor.sh
keep_files/test_basic.py
keep_files/use_bolor.py
keep_files/agent/__init__.py
keep_files/agent/dataset_loader.py
keep_files/agent/fixer.py
keep_files/agent/generator.py
keep_files/agent/llm_wrapper.py
keep_files/agent/models.py
keep_files/agent/planner.py
keep_files/agent/scanner.py
keep_files/evolution/__init__.py
keep_files/evolution/candidate.py
keep_files/utils/__init__.py
keep_files/utils/config.py
tests/__init__.py
tests/test_basic.py
bolor-0.2.7.dist-info/LICENSE
bolor-0.2.7.dist-info/METADATA
bolor-0.2.7.dist-info/WHEEL
bolor-0.2.7.dist-info/entry_points.txt
bolor-0.2.7.dist-info/top_level.txt
bolor-0.2.7.dist-info/RECORD
