Metadata-Version: 2.1
Name: bolor
Version: 0.2.7
Summary: Local LLM-based code repair tool with self-healing capabilities
Home-page: UNKNOWN
Author: Bolorerdene Bundgaa
Author-email: hi@photoxpedia.studio
License: MIT
Keywords: code-fix,debugging,llm,phi-2,repair,bug-fix
Platform: UNKNOWN
Classifier: Development Status :: 3 - Alpha
Classifier: Intended Audience :: Developers
Classifier: Topic :: Software Development :: Debuggers
Classifier: Programming Language :: Python :: 3
Classifier: Programming Language :: Python :: 3.8
Classifier: Programming Language :: Python :: 3.9
Classifier: Programming Language :: Python :: 3.10
Classifier: Programming Language :: Python :: 3.11
Classifier: License :: OSI Approved :: MIT License
Requires-Python: >=3.8
License-File: LICENSE
Requires-Dist: ctransformers>=0.2.0
Requires-Dist: langchain>=0.0.208
Requires-Dist: chromadb>=0.4.0
Requires-Dist: rich>=13.0.0
Requires-Dist: astunparse>=1.6.3
Requires-Dist: typer>=0.9.0
Requires-Dist: pytest>=7.0.0
Requires-Dist: urllib3<2.0.0,>=1.26.0
Requires-Dist: charset-normalizer<3.0.0,>=2.0.0
Requires-Dist: requests<3.0.0,>=2.25.0
